{
  "title": "My Story Title",
  "subtitle": "A subtitle about the story",
  "author": "Written for [Child's Name]",
  "pages": [
    {
      "title": "Page Title",
      "layout": "bottom-overlay",
      "img": "page_01.jpg",
      "text": "Write your story here. Use double newlines for paragraph breaks.\n\nLike this second paragraph."
    },
    {
      "title": "Page Two",
      "layout": "bottom-overlay",
      "img": "page_02.jpg",
      "text": "Each page should be 40\u201380 words, a complete narrative scene.\n\nTarget reading level: age 7\u20139."
    }
  ],
  "vocabulary": [
    {
      "word": "example",
      "pron": "/\u026a\u0261\u02c8z\u00e6m.p\u0259l/",
      "type": "noun",
      "zh": "\u4f8b\u5b50",
      "en": "A thing that shows what something is like"
    }
  ],
  "questions": [
    {
      "n": 1,
      "q": "Question text here?",
      "opts": [
        "A. First option",
        "B. Second option",
        "C. Third option",
        "D. Fourth option"
      ],
      "ans": "A",
      "text": "Correct answer explanation",
      "exp": "Detailed explanation and page reference"
    }
  ]
}
